hi_nicou11/__init__.py
hi_nicou11/hello.py
hi_Nicou11-0.8.0.dist-info/METADATA
hi_Nicou11-0.8.0.dist-info/WHEEL
hi_Nicou11-0.8.0.dist-info/entry_points.txt
hi_Nicou11-0.8.0.dist-info/top_level.txt
hi_Nicou11-0.8.0.dist-info/RECORD
