Metadata-Version: 2.1
Name: hi_Nicou11
Version: 0.8.0
Summary: Default template for PDM package
Author-email: Nicou11 <lyoungin1204@gmail.com>
License: MIT
Requires-Python: ==3.12.*
